file_archiver/__init__.py
file_archiver/archive.py
file_archiver/folder.py
file_archiver/py.typed
file_archiver-0.0.6.dist-info/LICENSE
file_archiver-0.0.6.dist-info/METADATA
file_archiver-0.0.6.dist-info/WHEEL
file_archiver-0.0.6.dist-info/RECORD
