Metadata-Version: 2.3
Name: file-archiver
Version: 0.0.6
Summary: Helper to create reproducible data-packages
License: MIT
Author: Luca Penasa
Author-email: luca.penasa@gmail.com
Requires-Python: >=3.10,<4.0
Classifier: Development Status :: 4 - Beta
Classifier: Intended Audience :: Developers
Classifier: License :: OSI Approved :: MIT License
Classifier: Operating System :: OS Independent
Classifier: Programming Language :: Python
Classifier: Programming Language :: Python :: 3
Classifier: Programming Language :: Python :: 3.10
Classifier: Programming Language :: Python :: 3.11
Classifier: Programming Language :: Python :: 3.12
Classifier: Programming Language :: Python :: 3.13
Classifier: Topic :: Software Development :: Libraries :: Python Modules
Classifier: Typing :: Typed
Requires-Dist: attrs (>=22.0.0)
Requires-Dist: cattrs (>=22.0.0)
Requires-Dist: importlib-metadata (>=8.5.0,<9.0.0)
Requires-Dist: loguru (>=0.7.2,<0.8.0)
Project-URL: Documentation, https://luca-penasa.github.io/file-archiver
Project-URL: Homepage, https://luca-penasa.github.io/file-archiver
Project-URL: Repository, https://github.com/luca-penasa/file-archiver
